assetgen/__init__.py
assetgen/build.py
assetgen/builders/__init__.py
assetgen/builders/console_schema_builder.py
assetgen/builders/docs_builder.py
assetgen/builders/helsinki_nlp_translation_map_builder.py
assetgen/builders/hf_configs_builder.py
assetgen/builders/readme_builder.py
assetgen/core/__init__.py
assetgen/core/rst_preprocessor.py
dgenerate/__init__.py
dgenerate/arguments.py
dgenerate/auto1111_metadata.py
dgenerate/config_icon.ico
dgenerate/devicecache.py
dgenerate/eval.py
dgenerate/events.py
dgenerate/exceptions.py
dgenerate/filecache.py
dgenerate/filelock.py
dgenerate/files.py
dgenerate/globalconfig.py
dgenerate/hfhub.py
dgenerate/icon.ico
dgenerate/image.py
dgenerate/invoker.py
dgenerate/mediainput.py
dgenerate/mediaoutput.py
dgenerate/memoize.py
dgenerate/memory.py
dgenerate/messages.py
dgenerate/plugin.py
dgenerate/prompt.py
dgenerate/pygments.py
dgenerate/release.json
dgenerate/renderloop.py
dgenerate/renderloopconfig.py
dgenerate/resources.py
dgenerate/spacycache.py
dgenerate/textprocessing.py
dgenerate/torchutil.py
dgenerate/types.py
dgenerate/webcache.py
dgenerate/_patches/__init__.py
dgenerate/_patches/accelerate_device_fallback_patch.py
dgenerate/_patches/diffusers_local_files_only_patch.py
dgenerate/_patches/diffusers_single_file_config_patch.py
dgenerate/_patches/hfhub_local_entry_missing_message_patch.py
dgenerate/_patches/tqdm_huggingface_hub_patch.py
dgenerate/_patches/transformers_dynamiccache_patch.py
dgenerate/batchprocess/__init__.py
dgenerate/batchprocess/auto1111_metadata_directive.py
dgenerate/batchprocess/batchprocessor.py
dgenerate/batchprocess/civitai_links_directive.py
dgenerate/batchprocess/configrunner.py
dgenerate/batchprocess/configrunnerbuiltins.py
dgenerate/batchprocess/configrunnerplugin.py
dgenerate/batchprocess/configrunnerpluginloader.py
dgenerate/batchprocess/image_process_directive.py
dgenerate/batchprocess/jinjabalancechecker.py
dgenerate/batchprocess/prompt_upscale_directive.py
dgenerate-5.0.0.dist-info/licenses/LICENSE
dgenerate-5.0.0.dist-info/METADATA
dgenerate-5.0.0.dist-info/WHEEL
dgenerate-5.0.0.dist-info/entry_points.txt
dgenerate-5.0.0.dist-info/top_level.txt
dgenerate-5.0.0.dist-info/RECORD
