Metadata-Version: 2.4
Name: dgenerate
Version: 5.0.0
Summary: Batch image generation and manipulation tool supporting Stable Diffusion and related techniques / algorithms, with support for video and animated image processing.
Home-page: https://github.com/Teriks/dgenerate
Author: Teriks
Author-email: Teriks@users.noreply.github.com
License: BSD 3-Clause
Classifier: Intended Audience :: Other Audience
Classifier: Intended Audience :: Science/Research
Classifier: Intended Audience :: Developers
Classifier: Natural Language :: English
Classifier: Operating System :: Microsoft :: Windows
Classifier: Operating System :: POSIX :: Linux
Classifier: Environment :: Console
Classifier: Environment :: GPU :: NVIDIA CUDA
Classifier: Topic :: Utilities
Classifier: Topic :: Artistic Software
Classifier: Topic :: Multimedia :: Graphics
Classifier: Topic :: Multimedia :: Video
Classifier: Topic :: Scientific/Engineering :: Artificial Intelligence
Classifier: Topic :: Scientific/Engineering :: Image Processing
Requires-Python: >=3.11,<3.14
License-File: LICENSE
Requires-Dist: diffusers==0.35.1
Requires-Dist: datasets==4.1.1
Requires-Dist: hf_xet<2.0.0,>=1.1.10
Requires-Dist: peft==0.17.1
Requires-Dist: transformers==4.55.2
Requires-Dist: accelerate==1.10.1
Requires-Dist: DeepCache==0.1.1
Requires-Dist: patchmatch-cython<0.2.0,>=0.1.4
Requires-Dist: dynamicprompts==0.31.0
Requires-Dist: spacy==3.8.7
Requires-Dist: dgenerate-ultralytics-headless==8.3.205
Requires-Dist: langcodes<4.0.0,>=3.5.0
Requires-Dist: pytorch-lightning<3.0.0,>=2.5.5
Requires-Dist: lightning-utilities<0.16.0,>=0.15.2
Requires-Dist: charset-normalizer<4.0.0,>=3.4.3
Requires-Dist: lightning-fabric<3.0.0,>=2.5.5
Requires-Dist: omegaconf<3.0.0,>=2.3.0
Requires-Dist: requests<3.0.0,>=2.32.5
Requires-Dist: av<16.0.0,>=15.0.0
Requires-Dist: pillow<12.0.0,>=11.3.0
Requires-Dist: piexif<2.0.0,>=1.1.3
Requires-Dist: jinja2<4.0.0,>=3.1.6
Requires-Dist: torch==2.8.0
Requires-Dist: torchvision==0.23.0
Requires-Dist: torchsde==0.2.6
Requires-Dist: fake-useragent==2.2.0
Requires-Dist: opencv-python-headless<5.0.0.0,>=4.12.0.88
Requires-Dist: psutil<8.0.0,>=7.1.0
Requires-Dist: sentencepiece<0.3.0,>=0.2.1
Requires-Dist: ftfy<7.0.0,>=6.3.1
Requires-Dist: beautifulsoup4<5.0.0,>=4.14.2
Requires-Dist: matplotlib<4.0.0,>=3.10.6
Requires-Dist: filelock<4.0.0,>=3.19.1
Requires-Dist: importlib_metadata<9.0.0,>=8.7.0
Requires-Dist: scipy<2.0.0,>=1.16.2
Requires-Dist: einops<0.9.0,>=0.8.1
Requires-Dist: timm<2.0.0,>=1.0.20
Requires-Dist: scikit-image<0.26.0,>=0.25.2
Requires-Dist: numpy<3.0.0,>=2.2.6
Requires-Dist: spandrel<0.5.0,>=0.4.1
Requires-Dist: spandrel_extra_arches<0.3.0,>=0.2.0
Requires-Dist: asteval<2.0.0,>=1.0.6
Requires-Dist: pygments<3.0.0,>=2.19.2
Requires-Dist: toml<0.11.0,>=0.10.2
Requires-Dist: tklinenums<2.0.0,>=1.7.1
Requires-Dist: pyrfc6266<2.0.0,>=1.0.2
Requires-Dist: protobuf<7.0.0,>=6.32.1
Requires-Dist: lark<2.0.0,>=1.3.0
Requires-Dist: packaging<26.0.0,>=25.0.0
Requires-Dist: ctranslate2<5.0.0,>=4.6.0
Requires-Dist: sacremoses==0.1.1
Requires-Dist: preshed<4.0.0,>=3.0.10
Provides-Extra: ncnn
Requires-Dist: ncnn==1.0.20250916; extra == "ncnn"
Provides-Extra: console-ui-opengl
Requires-Dist: pyopengltk==0.0.4; extra == "console-ui-opengl"
Requires-Dist: pyopengl==3.1.10; extra == "console-ui-opengl"
Requires-Dist: pyopengl-accelerate==3.1.10; extra == "console-ui-opengl"
Provides-Extra: gpt4all
Requires-Dist: gpt4all==2.8.2; extra == "gpt4all"
Provides-Extra: dev
Requires-Dist: sphinx-rtd-theme==3.0.2; extra == "dev"
Requires-Dist: poetry~=2.1.4; extra == "dev"
Provides-Extra: readthedocs
Requires-Dist: sphinx-rtd-theme==3.0.2; extra == "readthedocs"
Provides-Extra: bitsandbytes
Requires-Dist: bitsandbytes==0.48.1; extra == "bitsandbytes"
Provides-Extra: xformers
Requires-Dist: xformers==0.0.32.post2; extra == "xformers"
Provides-Extra: gpt4all-cuda
Requires-Dist: gpt4all[cuda]==2.8.2; extra == "gpt4all-cuda"
Provides-Extra: triton-windows
Requires-Dist: triton-windows==3.4.0.post20; extra == "triton-windows"
Dynamic: author
Dynamic: author-email
Dynamic: classifier
Dynamic: description
Dynamic: description-content-type
Dynamic: home-page
Dynamic: license
Dynamic: license-file
Dynamic: provides-extra
Dynamic: requires-dist
Dynamic: requires-python
Dynamic: summary
